susecloudlaunch/README.md
susecloudlaunch/__init__.py
susecloudlaunch/allproviderutil.py
susecloudlaunch/awsinstance.py
susecloudlaunch/azureinstance.py
susecloudlaunch/cloudlaunchinstance.py
susecloudlaunch/constants.py
susecloudlaunch/gcpinstance.py
susecloudlaunch/requirements.txt
susecloudlaunch/susecloudlaunch
susecloudlaunch/tf_templates/aws/instance.tf
susecloudlaunch/tf_templates/aws/network.tf
susecloudlaunch/tf_templates/aws/provider.tf
susecloudlaunch/tf_templates/aws/variables.tf
susecloudlaunch/tf_templates/azure/instance.tf
susecloudlaunch/tf_templates/azure/network.tf
susecloudlaunch/tf_templates/azure/provider.tf
susecloudlaunch/tf_templates/azure/variables.tf
susecloudlaunch/tf_templates/gcp/instance.tf
susecloudlaunch/tf_templates/gcp/network.tf
susecloudlaunch/tf_templates/gcp/provider.tf
susecloudlaunch/tf_templates/gcp/variables.tf
susecloudlaunch-0.9.0.dist-info/WHEEL
susecloudlaunch-0.9.0.dist-info/METADATA
susecloudlaunch-0.9.0.dist-info/RECORD
