Metadata-Version: 2.1
Name: susecloudlaunch
Version: 0.9.0
Summary: 
Author: Rich Paredes
Author-email: rich@suse.com
Requires-Python: >=3.6.1,<4.0.0
Classifier: Programming Language :: Python :: 3
Classifier: Programming Language :: Python :: 3.7
Classifier: Programming Language :: Python :: 3.8
Classifier: Programming Language :: Python :: 3.9
Requires-Dist: PyInquirer (>=1.0.3,<2.0.0)
Requires-Dist: azure-mgmt-compute (>=19.0.0,<20.0.0)
Requires-Dist: azure-mgmt-resource (>=15.0.0,<16.0.0)
Requires-Dist: azure-mgmt-subscription (>=1.0.0,<2.0.0)
Requires-Dist: boto3 (>=1.17.17,<2.0.0)
Requires-Dist: google-api-core (>=1.26.0,<2.0.0)
Requires-Dist: google-api-python-client (>=1.12.8,<2.0.0)
Requires-Dist: google-auth (>=1.27.0,<2.0.0)
Requires-Dist: google-auth-httplib2 (>=0.0.4,<0.0.5)
Requires-Dist: google-cloud-core (>=1.6.0,<2.0.0)
Requires-Dist: google-cloud-resource-manager (>=0.30.3,<0.31.0)
Requires-Dist: googleapis-common-protos (>=1.53.0,<2.0.0)
Requires-Dist: msrestazure (>=0.6.4,<0.7.0)
Requires-Dist: oauth2client (>=4.1.3,<5.0.0)
Requires-Dist: progress (>=1.5,<2.0)
Requires-Dist: python-terraform (>=0.10.1,<0.11.0)
